indusagi/__init__.py
indusagi/agency.py
indusagi/agent.py
indusagi/cli.py
indusagi/hooks.py
indusagi/memory.py
indusagi/orchestrator.py
indusagi/tool_usage_logger.py
indusagi/tools.py
indusagi/providers/__init__.py
indusagi/providers/anthropic_provider.py
indusagi/providers/base.py
indusagi/providers/openai_provider.py
indusagi/templates/__init__.py
indusagi/templates/renderer.py
indusagi/templates/scaffolder.py
indusagi/tools/__init__.py
indusagi/tools/base.py
indusagi/tools/handoff.py
indusagi/tools/dev/__init__.py
indusagi/tools/dev/bash.py
indusagi/tools/dev/edit.py
indusagi/tools/dev/glob.py
indusagi/tools/dev/grep.py
indusagi/tools/dev/read.py
indusagi/tools/dev/todo_write.py
indusagi/tools/dev/write.py
indusagi/utils/__init__.py
indusagi/utils/tool_converter.py
indusagi-0.2.0.dist-info/METADATA
indusagi-0.2.0.dist-info/WHEEL
indusagi-0.2.0.dist-info/entry_points.txt
indusagi-0.2.0.dist-info/licenses/LICENSE
indusagi-0.2.0.dist-info/RECORD
