Metadata-Version: 2.4
Name: indusagi
Version: 0.2.0
Summary: A modern, extensible indus-agents for building autonomous agents with LLMs
Project-URL: Homepage, https://github.com/varunisrani/indus-agents
Project-URL: Documentation, https://github.com/varunisrani/indus-agents#readme
Project-URL: Repository, https://github.com/varunisrani/indus-agents
Project-URL: Issues, https://github.com/varunisrani/indus-agents/issues
Project-URL: Changelog, https://github.com/varunisrani/indus-agents/blob/main/CHANGELOG.md
Author-email: IndusAGI Team <team@indusagi.ai>
Maintainer-email: IndusAGI Team <team@indusagi.ai>
License: MIT
License-File: LICENSE
Keywords: agent,ai,anthropic,assistant,autonomous-agents,chatbot,framework,function-calling,llm,openai,tool-use
Classifier: Development Status :: 3 - Alpha
Classifier: Intended Audience :: Developers
Classifier: Intended Audience :: Science/Research
Classifier: License :: OSI Approved :: MIT License
Classifier: Operating System :: OS Independent
Classifier: Programming Language :: Python :: 3
Classifier: Programming Language :: Python :: 3.9
Classifier: Programming Language :: Python :: 3.10
Classifier: Programming Language :: Python :: 3.11
Classifier: Programming Language :: Python :: 3.12
Classifier: Programming Language :: Python :: 3.13
Classifier: Topic :: Scientific/Engineering :: Artificial Intelligence
Classifier: Topic :: Software Development :: Libraries :: Application Frameworks
Classifier: Topic :: Software Development :: Libraries :: Python Modules
Classifier: Typing :: Typed
Requires-Python: >=3.9
Requires-Dist: anthropic<1.0.0,>=0.35.0
Requires-Dist: httpx<1.0.0,>=0.25.0
Requires-Dist: openai<2.0.0,>=1.0.0
Requires-Dist: pydantic-settings<3.0.0,>=2.0.0
Requires-Dist: pydantic<3.0.0,>=2.0.0
Requires-Dist: python-dotenv<2.0.0,>=1.0.0
Requires-Dist: rich<14.0.0,>=13.0.0
Requires-Dist: typer[all]<1.0.0,>=0.9.0
Provides-Extra: all
Requires-Dist: black<25.0.0,>=23.0.0; extra == 'all'
Requires-Dist: ipdb<1.0.0,>=0.13.0; extra == 'all'
Requires-Dist: ipython<9.0.0,>=8.0.0; extra == 'all'
Requires-Dist: mkdocs-material<10.0.0,>=9.0.0; extra == 'all'
Requires-Dist: mkdocs<2.0.0,>=1.5.0; extra == 'all'
Requires-Dist: mkdocstrings[python]<1.0.0,>=0.24.0; extra == 'all'
Requires-Dist: mypy<2.0.0,>=1.0.0; extra == 'all'
Requires-Dist: pre-commit<4.0.0,>=3.0.0; extra == 'all'
Requires-Dist: pytest-asyncio<1.0.0,>=0.21.0; extra == 'all'
Requires-Dist: pytest-cov<5.0.0,>=4.0.0; extra == 'all'
Requires-Dist: pytest-mock<4.0.0,>=3.12.0; extra == 'all'
Requires-Dist: pytest<8.0.0,>=7.0.0; extra == 'all'
Requires-Dist: ruff<1.0.0,>=0.1.0; extra == 'all'
Provides-Extra: dev
Requires-Dist: black<25.0.0,>=23.0.0; extra == 'dev'
Requires-Dist: ipdb<1.0.0,>=0.13.0; extra == 'dev'
Requires-Dist: ipython<9.0.0,>=8.0.0; extra == 'dev'
Requires-Dist: mypy<2.0.0,>=1.0.0; extra == 'dev'
Requires-Dist: pre-commit<4.0.0,>=3.0.0; extra == 'dev'
Requires-Dist: pytest-asyncio<1.0.0,>=0.21.0; extra == 'dev'
Requires-Dist: pytest-cov<5.0.0,>=4.0.0; extra == 'dev'
Requires-Dist: pytest-mock<4.0.0,>=3.12.0; extra == 'dev'
Requires-Dist: pytest<8.0.0,>=7.0.0; extra == 'dev'
Requires-Dist: ruff<1.0.0,>=0.1.0; extra == 'dev'
Provides-Extra: docs
Requires-Dist: mkdocs-material<10.0.0,>=9.0.0; extra == 'docs'
Requires-Dist: mkdocs<2.0.0,>=1.5.0; extra == 'docs'
Requires-Dist: mkdocstrings[python]<1.0.0,>=0.24.0; extra == 'docs'
